anomalysuite/__init__.py
anomalysuite-0.1.0.dist-info/licenses/LICENSE
anomalysuite-0.1.0.dist-info/METADATA
anomalysuite-0.1.0.dist-info/WHEEL
anomalysuite-0.1.0.dist-info/top_level.txt
anomalysuite-0.1.0.dist-info/RECORD
